pyp6/__init__.py
pyp6/access_db.py
pyp6/access_p6.py
pyp6/config.py
pyp6/utils.py
pyp6/scripts/__init__.py
pyp6/scripts/activities.py
pyp6/scripts/init.py
pyp6/scripts/obs.py
pyp6/scripts/roles.py
pyp6/scripts/wbs.py
pyp6-0.1.5.dist-info/licenses/LICENSE
pyp6-0.1.5.dist-info/METADATA
pyp6-0.1.5.dist-info/WHEEL
pyp6-0.1.5.dist-info/entry_points.txt
pyp6-0.1.5.dist-info/top_level.txt
pyp6-0.1.5.dist-info/RECORD
